deskAssistant/__init__.py
deskAssistant/deskAssistant.py
deskAssistant-0.0.8.dist-info/METADATA
deskAssistant-0.0.8.dist-info/WHEEL
deskAssistant-0.0.8.dist-info/top_level.txt
deskAssistant-0.0.8.dist-info/RECORD
