Metadata-Version: 2.1
Name: deskAssistant
Version: 0.0.8
Summary: A package to help with making a virtual assistant
Author: Blinken77YT
Author-email: theonilsson2012@icloud.com
Keywords: python,virtual,assistant,assistant virtual,virtual assistant
Classifier: Development Status :: 1 - Planning
Classifier: Intended Audience :: Developers
Classifier: Programming Language :: Python :: 3
Classifier: Operating System :: Unix
Classifier: Operating System :: MacOS :: MacOS X
Classifier: Operating System :: Microsoft :: Windows
Requires-Dist: pyttsx3
Requires-Dist: speechrecognition
Requires-Dist: pyaudio
Requires-Dist: datetime
